{
  "fips": "2502178690",
  "name": "Westwood",
  "county": "Norfolk County",
  "population": 16149,
  "grades": {
    "zoning": "F",
    "mbta": "A",
    "production": "D",
    "affordability": "D",
    "votes": null,
    "legislators": "A",
    "composite": "C"
  },
  "metrics": {
    "pct_land_multifamily_byright": 0.0,
    "median_home_value": 935200.0,
    "rent_burden_pct": 53.1,
    "permits_per_1000_residents": 0.87,
    "renter_share_pct": 13.7
  },
  "data_notes": {
    "zoning": null,
    "production": null,
    "affordability": null
  },
  "zoning_source": "nza",
  "mbta_status": "compliant",
  "mbta_deadline": "2024-12-31",
  "mbta_action_date": null,
  "reps": [
    {
      "name": "Paul McMurtry",
      "district": "11th Norfolk",
      "pct_score": 0.0,
      "grade": "F",
      "bills_scored": 1,
      "bills_available": 4,
      "sessions_scored": [
        "194"
      ]
    }
  ],
  "sens": [
    {
      "name": "Mike Rush",
      "district": "Norfolk and Suffolk",
      "pct_score": 100.0,
      "grade": "A",
      "bills_scored": 2,
      "bills_available": 2,
      "sessions_scored": [
        "193",
        "194"
      ]
    }
  ],
  "updated_at": "2026-04-08"
}